README.md
setup.py
lfdnn/__init__.py
lfdnn/numerical_tensor.py
lfdnn/operator.py
lfdnn/tensor.py
lfdnn/utils.py
lfdnn.egg-info/PKG-INFO
lfdnn.egg-info/SOURCES.txt
lfdnn.egg-info/dependency_links.txt
lfdnn.egg-info/requires.txt
lfdnn.egg-info/top_level.txt